<?xml version="1.0"?><results>
<header>
  <cloc_url>http://cloc.sourceforge.net</cloc_url>
  <cloc_version>1.56</cloc_version>
  <elapsed_seconds>0.5</elapsed_seconds>
  <n_files>9</n_files>
  <n_lines>407</n_lines>
  <files_per_second>18</files_per_second>
  <lines_per_second>814</lines_per_second>
  <report_file>C:\andiris29\13.SourceForge\antSoftware\personal.andrea.graceBI\trunk\dev\\ci\\cloc_result\as_CrossDomainAccessor.xml</report_file>
</header>
<languages>
  <language name="ActionScript" files_count="9" blank="56" comment="49" code="302" />
  <total sum_files="9" blank="56" comment="49" code="302" />
</languages>
</results>
